{
  "print": [
    {
      "title": "The Man Who Would Be King",
      "publication": "Art + Design",
      "image": "ck.jpg",
      "link": "/pdfs/calvin_klein.pdf"
    },
    {
      "title": "Journey to the Center of America",
      "publication": "Nylon",
      "image": "kansas.jpg",
      "link": "/pdfs/kansas.pdf"
    },
    {
      "title": "Ojai",
      "publication": "Cereal Magazine",
      "image": "cereal.jpg",
      "link": "/pdfs/cereal.pdf"
    },
    {
      "title": "Gorillaz in Their Midst",
      "publication": "Vanity Fair",
      "image": "gorillaz.jpg",
      "link": "http://www.vanityfair.com/culture/2013/08/gorillas-opera-monkey-journey-to-west"
    },
    {
      "title": "The Forgotten Coast",
      "publication": "Art + Design",
      "image": "coast.jpg",
      "link": "/pdfs/coast.pdf"
    },
    {
      "title": "Killer Solo",
      "publication": "Nylon",
      "image": "killer.jpg",
      "link": "/pdfs/killer_solo.pdf"
    },
    {
      "title": "Kinetic Energy",
      "publication": "The Window",
      "image": "kinetic.jpg",
      "link": "/pdfs/kinetic.pdf"
    },
    {
      "title": "Social Sculptor",
      "publication": "Art + Design",
      "image": "sculptor.jpg",
      "link": "/pdfs/sculptor.pdf"
    },
    {
      "title": "Simon Delestre",
      "publication": "Man of the World",
      "image": "simon.jpg",
      "link": "/pdfs/delestre.pdf"
    }
  ],
  "online": [
    {
      "title": "Santa Barbara",
      "publication": "cereal",
      "image": "sb.jpg",
      "link": "http://readcereal.com/santa-barbara/"
    },
    {
      "title": "Greatest Living Artists",
      "publication": "Vanity Fair",
      "image": "paint.jpg",
      "link": "http://www.vanityfair.com/culture/2013/11/greatest-living-artists-poll-results"
    },
    {
      "title": "Norma at the Met",
      "publication": "Vanity Fair",
      "image": "norma.jpg",
      "link": "http://www.vanityfair.com/culture/2013/10/norma-met-sondra-radvanovsky"
    },
    {
      "title": "Grace Slick",
      "publication": "Vanity Fair",
      "image": "grace.jpg",
      "link": "http://www.vanityfair.com/news/2012/06/jefferson-airplane-grace-slick-drugs-painting"
    },
    {
      "title": "Marie Colvin's Passport",
      "publication": "Vanity Fair",
      "image": "colvin.jpg",
      "link": "http://www.vanityfair.com/news/photos/2012/08/marie-colvin-passport-photos"
    },
    {
      "title": "Jo Nesbo",
      "publication": "Goodreads",
      "image": "nesbo.jpg",
      "link": "http://www.goodreads.com/interviews/show/929.Jo_Nesb_"
    }
  ],
  "cv": [
    {
      "title": "",
      "publication": "Click to Download",
      "image": "cv.jpg",
      "link": "/pdfs/MMSres18P.pdf"
    }
  ]
}
